[
  {
    "id": "booking-001",
    "userId": "user-001",
    "roomId": "room-001",
    "checkIn": "2024-12-20",
    "checkOut": "2024-12-23",
    "guests": 2,
    "status": "confirmed",
    "createdAt": "2024-11-15T10:00:00.000Z"
  },
  {
    "id": "booking-002",
    "userId": "user-001",
    "roomId": "room-004",
    "checkIn": "2025-01-10",
    "checkOut": "2025-01-14",
    "guests": 3,
    "status": "cancelled",
    "createdAt": "2024-11-20T14:30:00.000Z"
  },
  {
    "id": "booking-003",
    "userId": "user-001",
    "roomId": "room-012",
    "checkIn": "2024-10-05",
    "checkOut": "2024-10-08",
    "guests": 2,
    "status": "cancelled",
    "createdAt": "2024-09-01T09:00:00.000Z"
  },
  {
    "id": "bfd4fa86-ba95-43dd-be88-13dc272a3421",
    "userId": "admin-001",
    "roomId": "room-003",
    "checkIn": "2025-12-11",
    "checkOut": "2025-12-13",
    "guests": 1,
    "status": "cancelled",
    "createdAt": "2025-06-10T08:24:48.713Z"
  },
  {
    "id": "f617abbe-e7fe-4752-b942-9acdede2c11e",
    "userId": "user-001",
    "roomId": "room-013",
    "checkIn": "2025-12-11",
    "checkOut": "2025-12-12",
    "guests": 1,
    "status": "cancelled",
    "createdAt": "2025-06-10T08:28:03.307Z"
  },
  {
    "id": "10d7ffb0-3533-4c21-ac99-b6b11470e3ed",
    "userId": "user-001",
    "roomId": "room-012",
    "checkIn": "2026-06-13",
    "checkOut": "2026-06-14",
    "guests": 1,
    "status": "confirmed",
    "createdAt": "2026-06-10T09:50:27.062Z"
  }
]